[
    {
        "id": 17871191185706796,
        "created_at": 1588336383,
        "text": "So cute! What do you use to stuff it?",
        "owner": {
            "id": "6222284199",
            "is_verified": false,
            "profile_pic_url": "https://scontent-sin6-2.cdninstagram.com/v/t51.2885-19/s150x150/26865655_1632815143466634_6995835635885932544_n.jpg?_nc_ht=scontent-sin6-2.cdninstagram.com&_nc_ohc=QgQFv0fkHX4AX_gaVZI&oh=e74716d60fb9f868366fdbcf32a4117f&oe=5F2E455F",
            "username": "taromochi.bunnies"
        },
        "likes_count": 1,
        "answers": [
            {
                "id": 17864511142824675,
                "created_at": 1588337181,
                "text": "@taromochi.bunnies I had an old pillow I was gonna throw away! Just open up the seam and there\u2019s enough stuffing in there for many dozens of diy toys! \u263a\ufe0f",
                "owner": {
                    "id": "7542750448",
                    "is_verified": false,
                    "profile_pic_url": "https://scontent-sin6-2.cdninstagram.com/v/t51.2885-19/s150x150/33479939_929277133921314_6040934221231423488_n.jpg?_nc_ht=scontent-sin6-2.cdninstagram.com&_nc_ohc=7aaLBMhhgSoAX-4nekn&oh=3f7553889bf3103820b77d5c03826689&oe=5F2C7357",
                    "username": "artofasudden"
                },
                "likes_count": 1
            }
        ]
    },
    {
        "id": 17856718297932342,
        "created_at": 1588265184,
        "text": "You're so artistic!",
        "owner": {
            "id": "832398",
            "is_verified": false,
            "profile_pic_url": "https://scontent-sin6-2.cdninstagram.com/v/t51.2885-19/s150x150/69876753_392603511431210_1112771703647240192_n.jpg?_nc_ht=scontent-sin6-2.cdninstagram.com&_nc_ohc=AchNfHEc8xUAX99PwU6&oh=46ba92da835726342f76b7026c78fe49&oe=5F2E61D9",
            "username": "apriltolentino"
        },
        "likes_count": 1,
        "answers": []
    },
    {
        "id": 17852788681989011,
        "created_at": 1588253882,
        "text": "You are sooo talented",
        "owner": {
            "id": "1855084",
            "is_verified": false,
            "profile_pic_url": "https://scontent-sin6-2.cdninstagram.com/v/t51.2885-19/s150x150/14474200_1838682799694294_8883791916475351040_a.jpg?_nc_ht=scontent-sin6-2.cdninstagram.com&_nc_ohc=1IHAyPhI5rgAX-Dywls&oh=136f6380f2de3b663f604a3bebcd8f03&oe=5F2E6D61",
            "username": "kchanrai"
        },
        "likes_count": 1,
        "answers": []
    }
]