{
    "instaloader": {
        "node_type": "Post",
        "version": "4.4.4"
    },
    "node": {
        "__typename": "GraphVideo",
        "accessibility_caption": null,
        "caption_is_edited": false,
        "clips_music_attribution_info": null,
        "commenting_disabled_for_viewer": false,
        "comments_disabled": false,
        "dash_info": {
            "is_dash_eligible": false,
            "number_of_qualities": 0,
            "video_dash_manifest": null
        },
        "dimensions": {
            "height": 1333,
            "width": 750
        },
        "display_resources": [
            {
                "config_height": 1137,
                "config_width": 640,
                "src": "https://scontent-sin6-1.cdninstagram.com/v/t51.2885-15/sh0.08/e35/p640x640/94491329_246458630071115_2401449861335048777_n.jpg?_nc_ht=scontent-sin6-1.cdninstagram.com&_nc_cat=111&_nc_ohc=6IGGY2ft_hQAX9dxek0&oh=fb26b4b5544f9b70ee0d63650b8cb919&oe=5F0306B2"
            },
            {
                "config_height": 1333,
                "config_width": 750,
                "src": "https://scontent-sin6-1.cdninstagram.com/v/t51.2885-15/e35/94491329_246458630071115_2401449861335048777_n.jpg?_nc_ht=scontent-sin6-1.cdninstagram.com&_nc_cat=111&_nc_ohc=6IGGY2ft_hQAX9dxek0&oh=397dda1509d2c2f36c36b911b2761ac7&oe=5F034208"
            },
            {
                "config_height": 1920,
                "config_width": 1080,
                "src": "https://scontent-sin6-1.cdninstagram.com/v/t51.2885-15/e35/94491329_246458630071115_2401449861335048777_n.jpg?_nc_ht=scontent-sin6-1.cdninstagram.com&_nc_cat=111&_nc_ohc=6IGGY2ft_hQAX9dxek0&oh=397dda1509d2c2f36c36b911b2761ac7&oe=5F034208"
            }
        ],
        "display_url": "https://scontent-sin6-1.cdninstagram.com/v/t51.2885-15/e35/94491329_246458630071115_2401449861335048777_n.jpg?_nc_ht=scontent-sin6-1.cdninstagram.com&_nc_cat=111&_nc_ohc=6IGGY2ft_hQAX9dxek0&oh=397dda1509d2c2f36c36b911b2761ac7&oe=5F034208",
        "edge_media_preview_comment": {
            "count": 16,
            "edges": [
                {
                    "node": {
                        "created_at": 1587508992,
                        "did_report_as_spam": false,
                        "edge_liked_by": {
                            "count": 0
                        },
                        "id": "17898105472469135",
                        "is_restricted_pending": false,
                        "owner": {
                            "id": "25782226792",
                            "is_verified": false,
                            "profile_pic_url": "https://scontent-sin6-2.cdninstagram.com/v/t51.2885-19/s150x150/103796735_590213654965867_1642099621266899086_n.jpg?_nc_ht=scontent-sin6-2.cdninstagram.com&_nc_ohc=PFX4nBBZhUMAX8YEgZu&oh=2db3e2e6f10c9fac33cd7d10d251cb15&oe=5F2BC1DD",
                            "username": "hairyyyysg"
                        },
                        "text": "@jojimochis aku honestly tak sanggup duduk kat rumah lama ni macam. Modules aku aku dah tak faham",
                        "viewer_has_liked": false
                    }
                },
                {
                    "node": {
                        "created_at": 1587637359,
                        "did_report_as_spam": false,
                        "edge_liked_by": {
                            "count": 0
                        },
                        "id": "17865832000755382",
                        "is_restricted_pending": false,
                        "owner": {
                            "id": "8284930316",
                            "is_verified": false,
                            "profile_pic_url": "https://scontent-sin6-2.cdninstagram.com/v/t51.2885-19/s150x150/103373684_595076921127065_1578311293685902938_n.jpg?_nc_ht=scontent-sin6-2.cdninstagram.com&_nc_ohc=Orl830Nk7V8AX-zHT77&oh=625681c045d05b1c8e2bf7931cb27c61&oe=5F297A32",
                            "username": "norma_x_supreme_court"
                        },
                        "text": "Great job \ud83d\udc4d\ud83c\udffb u should go to china n experience the total lockdown like china Military communist style then u will appreciate Singapore c b Wic is lame in comparison",
                        "viewer_has_liked": false
                    }
                }
            ]
        },
        "edge_media_preview_like": {
            "count": 2900,
            "edges": []
        },
        "edge_media_to_caption": {
            "edges": [
                {
                    "node": {
                        "text": "On Apr. 21, PM Lee gave an update on the Covid-19 situation in Singapore, and annouced that the circuit breaker will be extended to June 1."
                    }
                }
            ]
        },
        "edge_media_to_comment": {
            "count": 16
        },
        "edge_media_to_hoisted_comment": {
            "edges": []
        },
        "edge_media_to_parent_comment": {
            "count": 16,
            "edges": [
                {
                    "node": {
                        "created_at": 1587466520,
                        "did_report_as_spam": false,
                        "edge_liked_by": {
                            "count": 2
                        },
                        "edge_threaded_comments": {
                            "count": 3,
                            "edges": [
                                {
                                    "node": {
                                        "created_at": 1587466643,
                                        "did_report_as_spam": false,
                                        "edge_liked_by": {
                                            "count": 0
                                        },
                                        "id": "17891144425496474",
                                        "is_restricted_pending": false,
                                        "owner": {
                                            "id": "13575918317",
                                            "is_verified": false,
                                            "profile_pic_url": "https://instagram.fyto1-1.fna.fbcdn.net/v/t51.2885-19/44884218_345707102882519_2446069589734326272_n.jpg?_nc_ht=instagram.fyto1-1.fna.fbcdn.net&_nc_ohc=0L7oBGC_n8wAX-_jbrg&oh=9c0e2c742f14ed4f4cecb8d94aab62dc&oe=5F2B678F&ig_cache_key=YW5vbnltb3VzX3Byb2ZpbGVfcGlj.2",
                                            "username": "jcbucketssfam"
                                        },
                                        "text": "@karterthevar \ud83e\udd21\ud83e\udd21\ud83e\udd21",
                                        "viewer_has_liked": false
                                    }
                                },
                                {
                                    "node": {
                                        "created_at": 1587466831,
                                        "did_report_as_spam": false,
                                        "edge_liked_by": {
                                            "count": 1
                                        },
                                        "id": "17885824642530830",
                                        "is_restricted_pending": false,
                                        "owner": {
                                            "id": "15236294110",
                                            "is_verified": false,
                                            "profile_pic_url": "https://scontent-sin6-2.cdninstagram.com/v/t51.2885-19/s150x150/100710764_248566949562883_6223659030699573248_n.jpg?_nc_ht=scontent-sin6-2.cdninstagram.com&_nc_ohc=624FwGyuUHgAX9lCwbC&oh=322bd39a4bcb9e8385370777bd214a27&oe=5F2B58E9",
                                            "username": "kakaverse"
                                        },
                                        "text": "@xman0015 PM lee doesnt wear blue,100% fake",
                                        "viewer_has_liked": false
                                    }
                                },
                                {
                                    "node": {
                                        "created_at": 1587467709,
                                        "did_report_as_spam": false,
                                        "edge_liked_by": {
                                            "count": 1
                                        },
                                        "id": "18115323703129330",
                                        "is_restricted_pending": false,
                                        "owner": {
                                            "id": "5428548171",
                                            "is_verified": false,
                                            "profile_pic_url": "https://scontent-sin6-2.cdninstagram.com/v/t51.2885-19/s150x150/83476453_2434352440149302_2204575638948413440_n.jpg?_nc_ht=scontent-sin6-2.cdninstagram.com&_nc_ohc=lkaK3bRIR4gAX8ilAJz&oh=76c2b234866dd74c6a2bc866a15066a3&oe=5F2B147E",
                                            "username": "karterthevar"
                                        },
                                        "text": "@kakaverse Lee Hsien Loong is not even real brother...",
                                        "viewer_has_liked": false
                                    }
                                }
                            ],
                            "page_info": {
                                "end_cursor": null,
                                "has_next_page": false
                            }
                        },
                        "id": "17851639759993788",
                        "is_restricted_pending": false,
                        "owner": {
                            "id": "5428548171",
                            "is_verified": false,
                            "profile_pic_url": "https://scontent-sin6-2.cdninstagram.com/v/t51.2885-19/s150x150/83476453_2434352440149302_2204575638948413440_n.jpg?_nc_ht=scontent-sin6-2.cdninstagram.com&_nc_ohc=lkaK3bRIR4gAX8ilAJz&oh=76c2b234866dd74c6a2bc866a15066a3&oe=5F2B147E",
                            "username": "karterthevar"
                        },
                        "text": "Fake",
                        "viewer_has_liked": false
                    }
                },
                {
                    "node": {
                        "created_at": 1587466555,
                        "did_report_as_spam": false,
                        "edge_liked_by": {
                            "count": 3
                        },
                        "edge_threaded_comments": {
                            "count": 0,
                            "edges": [],
                            "page_info": {
                                "end_cursor": null,
                                "has_next_page": false
                            }
                        },
                        "id": "17892718717483774",
                        "is_restricted_pending": false,
                        "owner": {
                            "id": "1438814338",
                            "is_verified": false,
                            "profile_pic_url": "https://scontent-sin6-2.cdninstagram.com/v/t51.2885-19/s150x150/106496679_3089471584506643_4902658867070216379_n.jpg?_nc_ht=scontent-sin6-2.cdninstagram.com&_nc_ohc=TXjbE7hjaw8AX-drGYz&oh=58625ca42786673a4b0123163fb2d90f&oe=5F2BAB78",
                            "username": "naywirqhh"
                        },
                        "text": "whrs president halimah \ud83d\ude14\ud83d\ude14",
                        "viewer_has_liked": false
                    }
                },
                {
                    "node": {
                        "created_at": 1587466568,
                        "did_report_as_spam": false,
                        "edge_liked_by": {
                            "count": 2
                        },
                        "edge_threaded_comments": {
                            "count": 2,
                            "edges": [
                                {
                                    "node": {
                                        "created_at": 1587471103,
                                        "did_report_as_spam": false,
                                        "edge_liked_by": {
                                            "count": 2
                                        },
                                        "id": "17877384670614737",
                                        "is_restricted_pending": false,
                                        "owner": {
                                            "id": "25609979075",
                                            "is_verified": false,
                                            "profile_pic_url": "https://scontent-sin6-2.cdninstagram.com/v/t51.2885-19/s150x150/100377382_1265758700482312_2523511788566216704_n.jpg?_nc_ht=scontent-sin6-2.cdninstagram.com&_nc_ohc=E71fjofFzv4AX_WaJZB&oh=43cab7447d3212718d34c30edaca6bbb&oe=5F2947BC",
                                            "username": "prataeggsatu"
                                        },
                                        "text": "@jojimochis I am wishing for the June Holidays to be school time. We can't have rest too much.",
                                        "viewer_has_liked": false
                                    }
                                },
                                {
                                    "node": {
                                        "created_at": 1587508992,
                                        "did_report_as_spam": false,
                                        "edge_liked_by": {
                                            "count": 0
                                        },
                                        "id": "17898105472469135",
                                        "is_restricted_pending": false,
                                        "owner": {
                                            "id": "25782226792",
                                            "is_verified": false,
                                            "profile_pic_url": "https://scontent-sin6-2.cdninstagram.com/v/t51.2885-19/s150x150/103796735_590213654965867_1642099621266899086_n.jpg?_nc_ht=scontent-sin6-2.cdninstagram.com&_nc_ohc=PFX4nBBZhUMAX8YEgZu&oh=2db3e2e6f10c9fac33cd7d10d251cb15&oe=5F2BC1DD",
                                            "username": "hairyyyysg"
                                        },
                                        "text": "@jojimochis aku honestly tak sanggup duduk kat rumah lama ni macam. Modules aku aku dah tak faham",
                                        "viewer_has_liked": false
                                    }
                                }
                            ],
                            "page_info": {
                                "end_cursor": null,
                                "has_next_page": false
                            }
                        },
                        "id": "17874072631642248",
                        "is_restricted_pending": false,
                        "owner": {
                            "id": "6068320593",
                            "is_verified": false,
                            "profile_pic_url": "https://scontent-sin6-2.cdninstagram.com/v/t51.2885-19/s150x150/106630412_578879689688725_4432140025186919138_n.jpg?_nc_ht=scontent-sin6-2.cdninstagram.com&_nc_ohc=MhAElWGyv_4AX9jTgDs&oh=d0c5beb71c7b77a48ebbc964a16f8096&oe=5F2A4862",
                            "username": "jojimochis"
                        },
                        "text": "lama giler korang cuti\ud83d\ude2d",
                        "viewer_has_liked": false
                    }
                },
                {
                    "node": {
                        "created_at": 1587466623,
                        "did_report_as_spam": false,
                        "edge_liked_by": {
                            "count": 4
                        },
                        "edge_threaded_comments": {
                            "count": 0,
                            "edges": [],
                            "page_info": {
                                "end_cursor": null,
                                "has_next_page": false
                            }
                        },
                        "id": "17845510523094809",
                        "is_restricted_pending": false,
                        "owner": {
                            "id": "7981068425",
                            "is_verified": false,
                            "profile_pic_url": "https://scontent-sin6-2.cdninstagram.com/v/t51.2885-19/s150x150/89610290_2638431196476334_3285742701193986048_n.jpg?_nc_ht=scontent-sin6-2.cdninstagram.com&_nc_ohc=T5QBbJhWs6UAX_lvt_d&oh=dc5f58bbc1c9d1b0925aeae6d4e8cbff&oe=5F2ACDA8",
                            "username": "youredeadtome__"
                        },
                        "text": "do yall think students will have to go back in june ?",
                        "viewer_has_liked": false
                    }
                },
                {
                    "node": {
                        "created_at": 1587468109,
                        "did_report_as_spam": false,
                        "edge_liked_by": {
                            "count": 5
                        },
                        "edge_threaded_comments": {
                            "count": 0,
                            "edges": [],
                            "page_info": {
                                "end_cursor": null,
                                "has_next_page": false
                            }
                        },
                        "id": "17855813893903492",
                        "is_restricted_pending": false,
                        "owner": {
                            "id": "33733612669",
                            "is_verified": false,
                            "profile_pic_url": "https://scontent-sin6-2.cdninstagram.com/v/t51.2885-19/s150x150/93807855_2721587717950745_8553971439261188096_n.jpg?_nc_ht=scontent-sin6-2.cdninstagram.com&_nc_ohc=VQ7-8RJCCC4AX-Ko0jP&oh=b22f70d90bf9429af5090e2e18df48cb&oe=5F2C29F7",
                            "username": "elisewong33"
                        },
                        "text": "Vote him out then no covid",
                        "viewer_has_liked": false
                    }
                },
                {
                    "node": {
                        "created_at": 1587471203,
                        "did_report_as_spam": false,
                        "edge_liked_by": {
                            "count": 0
                        },
                        "edge_threaded_comments": {
                            "count": 0,
                            "edges": [],
                            "page_info": {
                                "end_cursor": null,
                                "has_next_page": false
                            }
                        },
                        "id": "17875961758624883",
                        "is_restricted_pending": false,
                        "owner": {
                            "id": "12192842927",
                            "is_verified": false,
                            "profile_pic_url": "https://scontent-sin6-2.cdninstagram.com/v/t51.2885-19/s150x150/98146868_273803776994505_7473489084996911104_n.jpg?_nc_ht=scontent-sin6-2.cdninstagram.com&_nc_ohc=YG7l81Z3aLsAX_oIgGx&oh=dea49971d6ce152c02f36b29e6b45c99&oe=5F2BDD4F",
                            "username": "kowennnn"
                        },
                        "text": "open McDonalds",
                        "viewer_has_liked": false
                    }
                },
                {
                    "node": {
                        "created_at": 1587472413,
                        "did_report_as_spam": false,
                        "edge_liked_by": {
                            "count": 0
                        },
                        "edge_threaded_comments": {
                            "count": 0,
                            "edges": [],
                            "page_info": {
                                "end_cursor": null,
                                "has_next_page": false
                            }
                        },
                        "id": "17863392856787738",
                        "is_restricted_pending": false,
                        "owner": {
                            "id": "10948317833",
                            "is_verified": false,
                            "profile_pic_url": "https://scontent-sin6-2.cdninstagram.com/v/t51.2885-19/s150x150/104292577_915467562303264_7161469522003335101_n.jpg?_nc_ht=scontent-sin6-2.cdninstagram.com&_nc_ohc=ujtKObjsCIEAX_4wwrM&oh=519544769500e641dcfdc13b85bdc842&oe=5F2B15F4",
                            "username": "totallynotjoshuaaa"
                        },
                        "text": "S i p",
                        "viewer_has_liked": false
                    }
                },
                {
                    "node": {
                        "created_at": 1587476646,
                        "did_report_as_spam": false,
                        "edge_liked_by": {
                            "count": 0
                        },
                        "edge_threaded_comments": {
                            "count": 0,
                            "edges": [],
                            "page_info": {
                                "end_cursor": null,
                                "has_next_page": false
                            }
                        },
                        "id": "17948769691333921",
                        "is_restricted_pending": false,
                        "owner": {
                            "id": "7686403354",
                            "is_verified": false,
                            "profile_pic_url": "https://scontent-sin6-2.cdninstagram.com/v/t51.2885-19/s150x150/105942886_1912360085572520_6281201012736646937_n.jpg?_nc_ht=scontent-sin6-2.cdninstagram.com&_nc_ohc=n4P8995vNDcAX_q1NoD&oh=e66b486c24fc70e876a5790cc9b98591&oe=5F29491D",
                            "username": "r.rxxchel"
                        },
                        "text": "@julian.schulz i am gg to tag u when i see blue shirt \ud83d\udc55 \ud83e\udd75 // go see ur PM",
                        "viewer_has_liked": false
                    }
                },
                {
                    "node": {
                        "created_at": 1587487515,
                        "did_report_as_spam": false,
                        "edge_liked_by": {
                            "count": 3
                        },
                        "edge_threaded_comments": {
                            "count": 0,
                            "edges": [],
                            "page_info": {
                                "end_cursor": null,
                                "has_next_page": false
                            }
                        },
                        "id": "17853564058971349",
                        "is_restricted_pending": false,
                        "owner": {
                            "id": "4210156123",
                            "is_verified": false,
                            "profile_pic_url": "https://scontent-sin6-2.cdninstagram.com/v/t51.2885-19/s150x150/23734140_227047757833367_4928354622881398784_n.jpg?_nc_ht=scontent-sin6-2.cdninstagram.com&_nc_ohc=5yhutVz2KAIAX8LDdf3&oh=ca1fca798caeb7a8091e3bbb26b85288&oe=5F2AD51F",
                            "username": "huangqiae"
                        },
                        "text": "Cb government...",
                        "viewer_has_liked": false
                    }
                },
                {
                    "node": {
                        "created_at": 1587504336,
                        "did_report_as_spam": false,
                        "edge_liked_by": {
                            "count": 0
                        },
                        "edge_threaded_comments": {
                            "count": 0,
                            "edges": [],
                            "page_info": {
                                "end_cursor": null,
                                "has_next_page": false
                            }
                        },
                        "id": "18113560396117934",
                        "is_restricted_pending": false,
                        "owner": {
                            "id": "2912242983",
                            "is_verified": false,
                            "profile_pic_url": "https://scontent-sin6-2.cdninstagram.com/v/t51.2885-19/s150x150/106711964_2619260248288114_7768424487183989558_n.jpg?_nc_ht=scontent-sin6-2.cdninstagram.com&_nc_ohc=KmJY3DLHRUAAX_U_tFv&oh=73b879d3734cf663c6037d536268de99&oe=5F28D325",
                            "username": "joanne.carolyn"
                        },
                        "text": "@bertobrewcrew",
                        "viewer_has_liked": false
                    }
                },
                {
                    "node": {
                        "created_at": 1587637359,
                        "did_report_as_spam": false,
                        "edge_liked_by": {
                            "count": 0
                        },
                        "edge_threaded_comments": {
                            "count": 0,
                            "edges": [],
                            "page_info": {
                                "end_cursor": null,
                                "has_next_page": false
                            }
                        },
                        "id": "17865832000755382",
                        "is_restricted_pending": false,
                        "owner": {
                            "id": "8284930316",
                            "is_verified": false,
                            "profile_pic_url": "https://scontent-sin6-2.cdninstagram.com/v/t51.2885-19/s150x150/103373684_595076921127065_1578311293685902938_n.jpg?_nc_ht=scontent-sin6-2.cdninstagram.com&_nc_ohc=Orl830Nk7V8AX-zHT77&oh=625681c045d05b1c8e2bf7931cb27c61&oe=5F297A32",
                            "username": "norma_x_supreme_court"
                        },
                        "text": "Great job \ud83d\udc4d\ud83c\udffb u should go to china n experience the total lockdown like china Military communist style then u will appreciate Singapore c b Wic is lame in comparison",
                        "viewer_has_liked": false
                    }
                }
            ],
            "page_info": {
                "end_cursor": null,
                "has_next_page": false
            }
        },
        "edge_media_to_sponsor_user": {
            "edges": []
        },
        "edge_media_to_tagged_user": {
            "edges": []
        },
        "edge_related_profiles": {
            "edges": [
                {
                    "node": {
                        "edge_followed_by": {
                            "count": 645605
                        },
                        "edge_owner_to_timeline_media": {
                            "count": 9214,
                            "edges": [
                                {
                                    "node": {
                                        "__typename": "GraphVideo",
                                        "accessibility_caption": null,
                                        "edge_media_preview_comment": {
                                            "count": 47
                                        },
                                        "edge_media_preview_like": {
                                            "count": 6176
                                        },
                                        "gating_info": null,
                                        "id": "2345853936257138790",
                                        "is_video": true,
                                        "media_overlay_info": null,
                                        "owner": {
                                            "id": "293188374",
                                            "username": "sgagsg"
                                        },
                                        "shortcode": "CCOJbnljwBm",
                                        "thumbnail_src": "https://scontent-sin6-2.cdninstagram.com/v/t51.2885-15/e15/c0.77.612.612a/107033648_356917928627661_1263051519538606131_n.jpg?_nc_ht=scontent-sin6-2.cdninstagram.com&_nc_cat=1&_nc_ohc=_xs7yBWr3e4AX9kuykQ&oh=9350c296413ae7a501b92f729bfca6d5&oe=5F037B96"
                                    }
                                },
                                {
                                    "node": {
                                        "__typename": "GraphImage",
                                        "accessibility_caption": "Photo by SGAG on July 04, 2020. Image may contain: 1 person, text that says 'Trying to explain to my friend all the mind games the different political parties are playing Ale'",
                                        "edge_media_preview_comment": {
                                            "count": 84
                                        },
                                        "edge_media_preview_like": {
                                            "count": 17309
                                        },
                                        "gating_info": null,
                                        "id": "2345744457995206557",
                                        "is_video": false,
                                        "media_overlay_info": null,
                                        "owner": {
                                            "id": "293188374",
                                            "username": "sgagsg"
                                        },
                                        "shortcode": "CCNwigApT-d",
                                        "thumbnail_src": "https://scontent-sin6-1.cdninstagram.com/v/t51.2885-15/sh0.08/e35/c15.0.1159.1159a/s640x640/106299278_296583228150928_5036638261678046073_n.jpg?_nc_ht=scontent-sin6-1.cdninstagram.com&_nc_cat=104&_nc_ohc=299ciLTLtiQAX9sqyxn&oh=7a8ed22a2572f6fd21169661f7f686c1&oe=5F2C5305"
                                    }
                                },
                                {
                                    "node": {
                                        "__typename": "GraphImage",
                                        "accessibility_caption": "Photo by SGAG on July 04, 2020. Image may contain: 2 people, text that says 'Me during Phase 1: love you Ma, Pa, let's have dinner together! Me ever since Phase 2 started: SCAG'",
                                        "edge_media_preview_comment": {
                                            "count": 46
                                        },
                                        "edge_media_preview_like": {
                                            "count": 17520
                                        },
                                        "gating_info": null,
                                        "id": "2345736959821177873",
                                        "is_video": false,
                                        "media_overlay_info": null,
                                        "owner": {
                                            "id": "293188374",
                                            "username": "sgagsg"
                                        },
                                        "shortcode": "CCNu1YypWQR",
                                        "thumbnail_src": "https://scontent-sin6-2.cdninstagram.com/v/t51.2885-15/sh0.08/e35/c20.0.805.805a/s640x640/106500117_852677355138776_6656233757817924481_n.jpg?_nc_ht=scontent-sin6-2.cdninstagram.com&_nc_cat=108&_nc_ohc=XOpGE8cnBm4AX-BPkE1&oh=fd28c1e595a5187d8e32e14053183c15&oe=5F2AAB56"
                                    }
                                }
                            ]
                        },
                        "full_name": "SGAG",
                        "id": "293188374",
                        "is_private": false,
                        "is_verified": false,
                        "profile_pic_url": "https://scontent-sin6-2.cdninstagram.com/v/t51.2885-19/s150x150/91238139_384018682481353_6961916062946295808_n.jpg?_nc_ht=scontent-sin6-2.cdninstagram.com&_nc_ohc=GNE6dqyNRDUAX9peg4x&oh=9de8174f64acc56343a089b566c3e291&oe=5F2AE6F8",
                        "username": "sgagsg"
                    }
                },
                {
                    "node": {
                        "edge_followed_by": {
                            "count": 322578
                        },
                        "edge_owner_to_timeline_media": {
                            "count": 4211,
                            "edges": [
                                {
                                    "node": {
                                        "__typename": "GraphSidecar",
                                        "accessibility_caption": "Photo by The Straits Times on July 04, 2020. Image may contain: one or more people",
                                        "edge_media_preview_comment": {
                                            "count": 60
                                        },
                                        "edge_media_preview_like": {
                                            "count": 5151
                                        },
                                        "gating_info": null,
                                        "id": "2345713909225625205",
                                        "is_video": false,
                                        "media_overlay_info": null,
                                        "owner": {
                                            "id": "1091214028",
                                            "username": "straits_times"
                                        },
                                        "shortcode": "CCNpl9QFhZ1",
                                        "thumbnail_src": "https://scontent-sin6-2.cdninstagram.com/v/t51.2885-15/e15/c180.0.720.720a/s640x640/107101988_583181489059646_5839487649675837122_n.jpg?_nc_ht=scontent-sin6-2.cdninstagram.com&_nc_cat=102&_nc_ohc=qxLraqkZmWMAX_zuyUa&oh=6c6fe4584a6c898a6e1adb92c0990d67&oe=5F292C56"
                                    }
                                },
                                {
                                    "node": {
                                        "__typename": "GraphImage",
                                        "accessibility_caption": "Photo by The Straits Times in Singapore. Image may contain: text that says 'CORONAVIRUS RON Cinemas in Singapore can reopen from July 13 Putyou ST'",
                                        "edge_media_preview_comment": {
                                            "count": 264
                                        },
                                        "edge_media_preview_like": {
                                            "count": 15500
                                        },
                                        "gating_info": null,
                                        "id": "2345194674748291678",
                                        "is_video": false,
                                        "media_overlay_info": null,
                                        "owner": {
                                            "id": "1091214028",
                                            "username": "straits_times"
                                        },
                                        "shortcode": "CCLziGdgnpe",
                                        "thumbnail_src": "https://scontent-sin6-2.cdninstagram.com/v/t51.2885-15/sh0.08/e35/s640x640/106164012_303037577729018_7227658709187062928_n.jpg?_nc_ht=scontent-sin6-2.cdninstagram.com&_nc_cat=102&_nc_ohc=3c9jljjtIOkAX8QhP9v&oh=8655a00b90f635772da11b2799f49e99&oe=5F2BC499"
                                    }
                                },
                                {
                                    "node": {
                                        "__typename": "GraphImage",
                                        "accessibility_caption": "Photo by The Straits Times on July 03, 2020. Image may contain: one or more people, text that says 'CORONAVIRUS Hotels in Singapore can soon open for staycations ST'",
                                        "edge_media_preview_comment": {
                                            "count": 247
                                        },
                                        "edge_media_preview_like": {
                                            "count": 9970
                                        },
                                        "gating_info": null,
                                        "id": "2345045567008531225",
                                        "is_video": false,
                                        "media_overlay_info": null,
                                        "owner": {
                                            "id": "1091214028",
                                            "username": "straits_times"
                                        },
                                        "shortcode": "CCLRoTDpeMZ",
                                        "thumbnail_src": "https://scontent-sin6-1.cdninstagram.com/v/t51.2885-15/sh0.08/e35/s640x640/106303085_214323026370232_1502947435398671023_n.jpg?_nc_ht=scontent-sin6-1.cdninstagram.com&_nc_cat=104&_nc_ohc=IeM5PZwaAUUAX9llwAp&oh=0a86754f1b93b73d046642222382159b&oe=5F293B99"
                                    }
                                }
                            ]
                        },
                        "full_name": "The Straits Times",
                        "id": "1091214028",
                        "is_private": false,
                        "is_verified": true,
                        "profile_pic_url": "https://scontent-sin6-2.cdninstagram.com/v/t51.2885-19/s150x150/11925770_916199351788855_2049075909_a.jpg?_nc_ht=scontent-sin6-2.cdninstagram.com&_nc_ohc=xcEwWq_zyUUAX9-5cFa&oh=fa5f63bee8f105dc3894f636a7af0460&oe=5F29B41A",
                        "username": "straits_times"
                    }
                },
                {
                    "node": {
                        "edge_followed_by": {
                            "count": 55816
                        },
                        "edge_owner_to_timeline_media": {
                            "count": 5248,
                            "edges": [
                                {
                                    "node": {
                                        "__typename": "GraphImage",
                                        "accessibility_caption": "Photo by SgfollowsAll in The End Of The World. Image may contain: one or more people, text that says 'Haze may be thicker than last year PONHOTEL MUSTSHARENEWS.COM Haze May Hit S'pore Soon As Indonesia Reports 700 Fires, Keep Your Masks On Ah shit, here we go again.'",
                                        "edge_media_preview_comment": {
                                            "count": 30
                                        },
                                        "edge_media_preview_like": {
                                            "count": 2822
                                        },
                                        "gating_info": null,
                                        "id": "2345973004997465470",
                                        "is_video": false,
                                        "media_overlay_info": null,
                                        "owner": {
                                            "id": "8289801273",
                                            "username": "sgfollowsall"
                                        },
                                        "shortcode": "CCOkgS_h5V-",
                                        "thumbnail_src": "https://scontent-sin6-2.cdninstagram.com/v/t51.2885-15/sh0.08/e35/c0.128.1024.1024a/s640x640/106474362_280796683239969_8745775630126893800_n.jpg?_nc_ht=scontent-sin6-2.cdninstagram.com&_nc_cat=109&_nc_ohc=KBflZrz5txAAX-03iS1&oh=57009c98b135942e8a1ac93c58e1ac0d&oe=5F286FCA"
                                    }
                                },
                                {
                                    "node": {
                                        "__typename": "GraphImage",
                                        "accessibility_caption": "Photo by SgfollowsAll in Bedok North Road. Image may contain: outdoor",
                                        "edge_media_preview_comment": {
                                            "count": 30
                                        },
                                        "edge_media_preview_like": {
                                            "count": 2731
                                        },
                                        "gating_info": null,
                                        "id": "2345891083428584720",
                                        "is_video": false,
                                        "media_overlay_info": null,
                                        "owner": {
                                            "id": "8289801273",
                                            "username": "sgfollowsall"
                                        },
                                        "shortcode": "CCOR4LlhF0Q",
                                        "thumbnail_src": "https://scontent-sin6-2.cdninstagram.com/v/t51.2885-15/sh0.08/e35/s640x640/106580409_2692380261018603_7269455019085159375_n.jpg?_nc_ht=scontent-sin6-2.cdninstagram.com&_nc_cat=103&_nc_ohc=6L_MBibZTz0AX_X62y8&oh=d732b9a47dcd18f65d3791291ca3732e&oe=5F2C4F7B"
                                    }
                                },
                                {
                                    "node": {
                                        "__typename": "GraphSidecar",
                                        "accessibility_caption": null,
                                        "edge_media_preview_comment": {
                                            "count": 113
                                        },
                                        "edge_media_preview_like": {
                                            "count": 4279
                                        },
                                        "gating_info": null,
                                        "id": "2345877397834079405",
                                        "is_video": false,
                                        "media_overlay_info": null,
                                        "owner": {
                                            "id": "8289801273",
                                            "username": "sgfollowsall"
                                        },
                                        "shortcode": "CCOOxB4hJyt",
                                        "thumbnail_src": "https://scontent-sin6-2.cdninstagram.com/v/t51.2885-15/e35/106152875_108183307536500_6750335487203911306_n.jpg?_nc_ht=scontent-sin6-2.cdninstagram.com&_nc_cat=108&_nc_ohc=EDgXTYcyxMoAX-wQEt3&oh=a06285e48893675382fe63ace1db84f8&oe=5F03666E"
                                    }
                                }
                            ]
                        },
                        "full_name": "SgfollowsAll",
                        "id": "8289801273",
                        "is_private": false,
                        "is_verified": false,
                        "profile_pic_url": "https://scontent-sin6-2.cdninstagram.com/v/t51.2885-19/s150x150/55899991_320593665323551_3137774987583160320_n.jpg?_nc_ht=scontent-sin6-2.cdninstagram.com&_nc_ohc=TPxJ4Vi7PvAAX9XQM3F&oh=996bb79cc8d3a8921600e66a75f4399c&oe=5F29B5D3",
                        "username": "sgfollowsall"
                    }
                },
                {
                    "node": {
                        "edge_followed_by": {
                            "count": 148607
                        },
                        "edge_owner_to_timeline_media": {
                            "count": 4924,
                            "edges": [
                                {
                                    "node": {
                                        "__typename": "GraphImage",
                                        "accessibility_caption": "Photo by TODAY on July 04, 2020. Image may contain: 2 people, text",
                                        "edge_media_preview_comment": {
                                            "count": 2
                                        },
                                        "edge_media_preview_like": {
                                            "count": 589
                                        },
                                        "gating_info": null,
                                        "id": "2345899485458101918",
                                        "is_video": false,
                                        "media_overlay_info": null,
                                        "owner": {
                                            "id": "199148173",
                                            "username": "todayonline"
                                        },
                                        "shortcode": "CCOTyclgHae",
                                        "thumbnail_src": "https://scontent-sin6-1.cdninstagram.com/v/t51.2885-15/sh0.08/e35/s640x640/106242450_160422242274486_8697697441714071772_n.jpg?_nc_ht=scontent-sin6-1.cdninstagram.com&_nc_cat=106&_nc_ohc=UbVNCdqsYPQAX9ezK7K&oh=fcf9ea04ec163bea0f23ce204b170fd9&oe=5F2B383F"
                                    }
                                },
                                {
                                    "node": {
                                        "__typename": "GraphImage",
                                        "accessibility_caption": "Photo by TODAY on July 04, 2020. Image may contain: 4 people, text that says 'Qi Yuwu shows his funny side during a virtual press conference for A Quest to Heal'",
                                        "edge_media_preview_comment": {
                                            "count": 0
                                        },
                                        "edge_media_preview_like": {
                                            "count": 697
                                        },
                                        "gating_info": null,
                                        "id": "2345884405024561909",
                                        "is_video": false,
                                        "media_overlay_info": null,
                                        "owner": {
                                            "id": "199148173",
                                            "username": "todayonline"
                                        },
                                        "shortcode": "CCOQW_1nhr1",
                                        "thumbnail_src": "https://scontent-sin6-2.cdninstagram.com/v/t51.2885-15/sh0.08/e35/s640x640/106711965_164940798407385_7430561295475778080_n.jpg?_nc_ht=scontent-sin6-2.cdninstagram.com&_nc_cat=109&_nc_ohc=3hSK1p4TR1oAX8349T-&oh=cf93a5f7151eeef46f646eae56307379&oe=5F2AC0B8"
                                    }
                                },
                                {
                                    "node": {
                                        "__typename": "GraphVideo",
                                        "accessibility_caption": null,
                                        "edge_media_preview_comment": {
                                            "count": 9
                                        },
                                        "edge_media_preview_like": {
                                            "count": 560
                                        },
                                        "gating_info": null,
                                        "id": "2345864101850613045",
                                        "is_video": true,
                                        "media_overlay_info": null,
                                        "owner": {
                                            "id": "199148173",
                                            "username": "todayonline"
                                        },
                                        "shortcode": "CCOLvjCJYU1",
                                        "thumbnail_src": "https://scontent-sin6-1.cdninstagram.com/v/t51.2885-15/e15/c0.280.720.720a/s640x640/106411980_983065838783106_8690120037310034593_n.jpg?_nc_ht=scontent-sin6-1.cdninstagram.com&_nc_cat=106&_nc_ohc=orYGzuWjsp8AX9X8Ciq&oh=1499d01487d145a46e0d5c4ed4918141&oe=5F032DC5"
                                    }
                                }
                            ]
                        },
                        "full_name": "TODAY",
                        "id": "199148173",
                        "is_private": false,
                        "is_verified": true,
                        "profile_pic_url": "https://scontent-sin6-2.cdninstagram.com/v/t51.2885-19/11007793_341391156049463_531885097_a.jpg?_nc_ht=scontent-sin6-2.cdninstagram.com&_nc_ohc=Z6Ri00Pqi8MAX8AiiZS&oh=9f02f766584a2b52914ae5b5edc8fca3&oe=5F2B1BBC",
                        "username": "todayonline"
                    }
                },
                {
                    "node": {
                        "edge_followed_by": {
                            "count": 55179
                        },
                        "edge_owner_to_timeline_media": {
                            "count": 935,
                            "edges": [
                                {
                                    "node": {
                                        "__typename": "GraphImage",
                                        "accessibility_caption": "Photo by Wake Up, Singapore \ud83c\uddf8\ud83c\uddec on July 04, 2020. Image may contain: 8 people, meme, text that says 'IF MASAGOS WAS A NORTH KOREAN POLITICIAN \"LAST YEAR AT OUR PARTY RALLY, KIM JONGNAM OUR SUPREME LEADER--\" YES, DEATH BY FIRING SQUAD'",
                                        "edge_media_preview_comment": {
                                            "count": 16
                                        },
                                        "edge_media_preview_like": {
                                            "count": 3084
                                        },
                                        "gating_info": null,
                                        "id": "2345797756909739840",
                                        "is_video": false,
                                        "media_overlay_info": null,
                                        "owner": {
                                            "id": "2905045724",
                                            "username": "wakeupsingapore"
                                        },
                                        "shortcode": "CCN8qGfg19A",
                                        "thumbnail_src": "https://scontent-sin6-2.cdninstagram.com/v/t51.2885-15/sh0.08/e35/c0.81.1080.1080a/s640x640/106346945_289219825531028_5697922340994742016_n.jpg?_nc_ht=scontent-sin6-2.cdninstagram.com&_nc_cat=108&_nc_ohc=MY-2osTWDogAX_MlU3m&oh=42ef4dfe02e6a264a89284a9439e57c3&oe=5F2C3194"
                                    }
                                },
                                {
                                    "node": {
                                        "__typename": "GraphSidecar",
                                        "accessibility_caption": "Photo by Wake Up, Singapore \ud83c\uddf8\ud83c\uddec on July 04, 2020. Image may contain: text",
                                        "edge_media_preview_comment": {
                                            "count": 5
                                        },
                                        "edge_media_preview_like": {
                                            "count": 1436
                                        },
                                        "gating_info": null,
                                        "id": "2345730634942562928",
                                        "is_video": false,
                                        "media_overlay_info": null,
                                        "owner": {
                                            "id": "2905045724",
                                            "username": "wakeupsingapore"
                                        },
                                        "shortcode": "CCNtZWSgMJw",
                                        "thumbnail_src": "https://scontent-sin6-1.cdninstagram.com/v/t51.2885-15/sh0.08/e35/s640x640/83259282_366824240961688_3551277344533702419_n.jpg?_nc_ht=scontent-sin6-1.cdninstagram.com&_nc_cat=104&_nc_ohc=6q1JqZCr7ZIAX-F01pD&oh=a117c32dbb3ca04de13d889be5cdfc5f&oe=5F29156A"
                                    }
                                },
                                {
                                    "node": {
                                        "__typename": "GraphImage",
                                        "accessibility_caption": "Photo by Wake Up, Singapore \ud83c\uddf8\ud83c\uddec in Ang Mo Kio, Singapore. Image may contain: 10 people",
                                        "edge_media_preview_comment": {
                                            "count": 12
                                        },
                                        "edge_media_preview_like": {
                                            "count": 3067
                                        },
                                        "gating_info": null,
                                        "id": "2345608976680554725",
                                        "is_video": false,
                                        "media_overlay_info": null,
                                        "owner": {
                                            "id": "2905045724",
                                            "username": "wakeupsingapore"
                                        },
                                        "shortcode": "CCNRu_NAxDl",
                                        "thumbnail_src": "https://scontent-sin6-2.cdninstagram.com/v/t51.2885-15/e15/c35.0.1009.1009a/s640x640/106922982_107427230957890_5438962867954498793_n.jpg?_nc_ht=scontent-sin6-2.cdninstagram.com&_nc_cat=110&_nc_ohc=zGl6ADGWS-gAX8Ysnx_&oh=74af5fdaad77cce7e883e6bb84fe546e&oe=5F29A4A7"
                                    }
                                }
                            ]
                        },
                        "full_name": "Wake Up, Singapore \ud83c\uddf8\ud83c\uddec",
                        "id": "2905045724",
                        "is_private": false,
                        "is_verified": false,
                        "profile_pic_url": "https://scontent-sin6-2.cdninstagram.com/v/t51.2885-19/s150x150/55778152_1025315437668600_5134898582238789632_n.jpg?_nc_ht=scontent-sin6-2.cdninstagram.com&_nc_ohc=YEMnVOPyCXgAX8Rbzq9&oh=cc611608e11d77ee0e308509fce5cc08&oe=5F29606D",
                        "username": "wakeupsingapore"
                    }
                },
                {
                    "node": {
                        "edge_followed_by": {
                            "count": 260251
                        },
                        "edge_owner_to_timeline_media": {
                            "count": 2628,
                            "edges": [
                                {
                                    "node": {
                                        "__typename": "GraphSidecar",
                                        "accessibility_caption": null,
                                        "edge_media_preview_comment": {
                                            "count": 29
                                        },
                                        "edge_media_preview_like": {
                                            "count": 6603
                                        },
                                        "gating_info": null,
                                        "id": "2345602947203125568",
                                        "is_video": false,
                                        "media_overlay_info": null,
                                        "owner": {
                                            "id": "363956201",
                                            "username": "nightowlcinematics"
                                        },
                                        "shortcode": "CCNQXP0JtFA",
                                        "thumbnail_src": "https://scontent-sin6-2.cdninstagram.com/v/t51.2885-15/e35/c90.0.540.540a/106414551_2335034320135781_1381631515214625917_n.jpg?_nc_ht=scontent-sin6-2.cdninstagram.com&_nc_cat=105&_nc_ohc=O1iTK0T5Kl4AX__69V9&oh=7f61a2e4cdab6e160197acb42cf8de1b&oe=5F035E79"
                                    }
                                },
                                {
                                    "node": {
                                        "__typename": "GraphVideo",
                                        "accessibility_caption": null,
                                        "edge_media_preview_comment": {
                                            "count": 78
                                        },
                                        "edge_media_preview_like": {
                                            "count": 8878
                                        },
                                        "gating_info": null,
                                        "id": "2345129690275327871",
                                        "is_video": true,
                                        "media_overlay_info": null,
                                        "owner": {
                                            "id": "363956201",
                                            "username": "nightowlcinematics"
                                        },
                                        "shortcode": "CCLkwc9FS9_",
                                        "thumbnail_src": "https://scontent-sin6-2.cdninstagram.com/v/t51.2885-15/e15/c0.85.720.720a/s640x640/106700795_1462592483921133_1051372822207468788_n.jpg?_nc_ht=scontent-sin6-2.cdninstagram.com&_nc_cat=109&_nc_ohc=WR_3DOGBmCQAX_bfuv_&oh=8dfb9a2ba59596039e67499d1a7cbb15&oe=5F030854"
                                    }
                                },
                                {
                                    "node": {
                                        "__typename": "GraphImage",
                                        "accessibility_caption": "Photo shared by NOC By Ryan Sylvia! on July 03, 2020 tagging @aikenchia, @foodkingnoc, and @ryanxgo. Image may contain: 3 people, people eating, people sitting, table and food",
                                        "edge_media_preview_comment": {
                                            "count": 39
                                        },
                                        "edge_media_preview_like": {
                                            "count": 6221
                                        },
                                        "gating_info": null,
                                        "id": "2344960772870157984",
                                        "is_video": false,
                                        "media_overlay_info": null,
                                        "owner": {
                                            "id": "363956201",
                                            "username": "nightowlcinematics"
                                        },
                                        "shortcode": "CCK-WYXJrag",
                                        "thumbnail_src": "https://scontent-sin6-2.cdninstagram.com/v/t51.2885-15/sh0.08/e35/s640x640/107076096_609998736303518_1794126570355221127_n.jpg?_nc_ht=scontent-sin6-2.cdninstagram.com&_nc_cat=102&_nc_ohc=QF7S_mDsfU8AX8F-BAD&oh=a9d59b47a346e72bf671830fc67ce7eb&oe=5F2BFC13"
                                    }
                                }
                            ]
                        },
                        "full_name": "NOC By Ryan Sylvia!",
                        "id": "363956201",
                        "is_private": false,
                        "is_verified": true,
                        "profile_pic_url": "https://scontent-sin6-2.cdninstagram.com/v/t51.2885-19/s150x150/92320984_313264596312294_5485424847678865408_n.jpg?_nc_ht=scontent-sin6-2.cdninstagram.com&_nc_ohc=jO1LTpFAwo4AX9kbH6V&oh=d64b5f2cf0ecfc34d28ffa766f171dd2&oe=5F2BB2C9",
                        "username": "nightowlcinematics"
                    }
                }
            ]
        },
        "edge_web_media_to_related_media": {
            "edges": []
        },
        "encoding_status": null,
        "fact_check_information": null,
        "fact_check_overall_rating": null,
        "gating_info": null,
        "has_audio": true,
        "has_ranked_comments": false,
        "id": "2292154488193870699",
        "is_ad": false,
        "is_published": true,
        "is_video": true,
        "location": null,
        "media_overlay_info": null,
        "media_preview": "ABcqV2DLkVD5fy7qlMbBehqv8/3MVHLft82WnbuWoFBXmikibYMPwaKWi0Y9xtwztGQR1xjBz/8AqHH50RghgxI2+nPpz26+tMVm7gflUzrgbuOO2P8A69O9hMimYF8jpxRSKC4ycflRUOOpSZPgU1z8prPDH1NBJxV2IuXkTAFFU1JxRTsFz//Z",
        "owner": {
            "biography": "The younger people run this account.",
            "blocked_by_viewer": false,
            "business_category_name": "Publishers",
            "category_enum": "NEWS_SITE",
            "connected_fb_page": null,
            "country_block": false,
            "edge_follow": {
                "count": 354
            },
            "edge_followed_by": {
                "count": 298048
            },
            "edge_mutual_followed_by": {
                "count": 0,
                "edges": []
            },
            "edge_related_profiles": {
                "edges": []
            },
            "external_url": "https://linkinprofile.com/mothershipsg",
            "external_url_linkshimmed": "https://l.instagram.com/?u=https%3A%2F%2Flinkinprofile.com%2Fmothershipsg&e=ATMKOOJHRxdqgN9bl2mKMkdx_tsdpG6NyuZM8MHqqHa0oOlHRmG01NOPRjtlWFKRpHWSjjL3nQCDOkwl&s=1",
            "followed_by_viewer": false,
            "follows_viewer": false,
            "full_name": "Mothership.sg",
            "has_ar_effects": false,
            "has_blocked_viewer": false,
            "has_channel": false,
            "has_requested_viewer": false,
            "highlight_reel_count": 56,
            "id": "479894638",
            "is_business_account": true,
            "is_joined_recently": false,
            "is_private": false,
            "is_verified": true,
            "overall_category_name": null,
            "profile_pic_url": "https://scontent-sin6-2.cdninstagram.com/v/t51.2885-19/s150x150/91398632_809699462851271_12838593550614528_n.jpg?_nc_ht=scontent-sin6-2.cdninstagram.com&_nc_ohc=fiay2vLYHQEAX8WFuVV&oh=125817c086fca4da6907479d4e84f028&oe=5F28E513",
            "profile_pic_url_hd": "https://scontent-sin6-2.cdninstagram.com/v/t51.2885-19/s320x320/91398632_809699462851271_12838593550614528_n.jpg?_nc_ht=scontent-sin6-2.cdninstagram.com&_nc_ohc=fiay2vLYHQEAX8WFuVV&oh=aef574a120485afb877c86c84d3bc602&oe=5F2AA66D",
            "requested_by_viewer": false,
            "restricted_by_viewer": null,
            "username": "mothershipsg"
        },
        "product_type": "igtv",
        "sensitivity_friction_info": null,
        "shortcode": "B_PXlzXHOtr",
        "taken_at_timestamp": 1587466489,
        "thumbnail_resources": [
            {
                "config_height": 266,
                "config_width": 150,
                "src": "https://scontent-sin6-1.cdninstagram.com/v/t51.2885-15/e35/p150x150/94491329_246458630071115_2401449861335048777_n.jpg?_nc_ht=scontent-sin6-1.cdninstagram.com&_nc_cat=111&_nc_ohc=6IGGY2ft_hQAX9dxek0&oh=6f673c05eee65e1a50c08561be8be919&oe=5F036457"
            },
            {
                "config_height": 426,
                "config_width": 240,
                "src": "https://scontent-sin6-1.cdninstagram.com/v/t51.2885-15/e35/p240x240/94491329_246458630071115_2401449861335048777_n.jpg?_nc_ht=scontent-sin6-1.cdninstagram.com&_nc_cat=111&_nc_ohc=6IGGY2ft_hQAX9dxek0&oh=03ff43ec57851930b52ac9de2d6246a3&oe=5F031ADD"
            },
            {
                "config_height": 568,
                "config_width": 320,
                "src": "https://scontent-sin6-1.cdninstagram.com/v/t51.2885-15/e35/p320x320/94491329_246458630071115_2401449861335048777_n.jpg?_nc_ht=scontent-sin6-1.cdninstagram.com&_nc_cat=111&_nc_ohc=6IGGY2ft_hQAX9dxek0&oh=583343b91c4ff6e62bfbbab85f5ed306&oe=5F032AE7"
            },
            {
                "config_height": 853,
                "config_width": 480,
                "src": "https://scontent-sin6-1.cdninstagram.com/v/t51.2885-15/e35/p480x480/94491329_246458630071115_2401449861335048777_n.jpg?_nc_ht=scontent-sin6-1.cdninstagram.com&_nc_cat=111&_nc_ohc=6IGGY2ft_hQAX9dxek0&oh=b7b0cd82fb1642860a064dea9a251bcb&oe=5F03403D"
            },
            {
                "config_height": 1137,
                "config_width": 640,
                "src": "https://scontent-sin6-1.cdninstagram.com/v/t51.2885-15/sh0.08/e35/p640x640/94491329_246458630071115_2401449861335048777_n.jpg?_nc_ht=scontent-sin6-1.cdninstagram.com&_nc_cat=111&_nc_ohc=6IGGY2ft_hQAX9dxek0&oh=fb26b4b5544f9b70ee0d63650b8cb919&oe=5F0306B2"
            }
        ],
        "thumbnail_src": "https://scontent-sin6-1.cdninstagram.com/v/t51.2885-15/sh0.08/e35/c0.280.720.720a/s640x640/94491329_246458630071115_2401449861335048777_n.jpg?_nc_ht=scontent-sin6-1.cdninstagram.com&_nc_cat=111&_nc_ohc=6IGGY2ft_hQAX9dxek0&oh=c1bd09402f0271b4f18d1a5e8bb55e44&oe=5F033437",
        "title": "[PART 1] Circuit Breaker Extended to June 1",
        "tracking_token": "eyJ2ZXJzaW9uIjo1LCJwYXlsb2FkIjp7ImlzX2FuYWx5dGljc190cmFja2VkIjp0cnVlLCJ1dWlkIjoiYzc5YjYzZWM3YjAyNDcxNGEzZmE1NjA4ZWE4OTgyYzAyMjkyMTU0NDg4MTkzODcwNjk5In0sInNpZ25hdHVyZSI6IiJ9",
        "video_duration": 400.966,
        "video_play_count": null,
        "video_url": "https://scontent-sin6-2.cdninstagram.com/v/t50.16885-16/10000000_355097432112934_805388607266004543_n.mp4?_nc_ht=scontent-sin6-2.cdninstagram.com&_nc_cat=110&_nc_ohc=SA_tx2TAqG0AX8aX-xA&oe=5F0327CC&oh=205c0251924525a9f49918dfac772adb",
        "video_view_count": 20089,
        "viewer_can_reshare": true,
        "viewer_has_liked": false,
        "viewer_has_saved": false,
        "viewer_has_saved_to_collection": false,
        "viewer_in_photo_of_you": false
    }
}